transfer_phone/pjtTransferDictionary.pkl
transfer_phone/transfer_phone.py
transfer_phone-1.4.dist-info/METADATA
transfer_phone-1.4.dist-info/WHEEL
transfer_phone-1.4.dist-info/top_level.txt
transfer_phone-1.4.dist-info/RECORD
