Metadata-Version: 2.1
Name: transfer_phone
Version: 1.4
Summary: Defect relation mapping
Home-page: https://github.com/tieyongjie/transfer_phone
Author: White.tie
Author-email: 1042798703@qq.com
Classifier: Environment :: Web Environment
Classifier: Intended Audience :: Developers
Classifier: Operating System :: OS Independent
Classifier: Topic :: Text Processing :: Indexing
Classifier: Topic :: Utilities
Classifier: Topic :: Internet
Classifier: Topic :: Software Development :: Libraries :: Python Modules
Classifier: Programming Language :: Python
Classifier: Programming Language :: Python :: 3.7
Classifier: Programming Language :: Python :: 3.8
Classifier: Programming Language :: Python :: 3.9
